LICENSE
MANIFEST.in
README.rst
buildout.cfg
develop.cfg
pyproject.toml
requirements.txt
setup.py
version.txt
bob/__init__.py
bob.learn.activation.egg-info/PKG-INFO
bob.learn.activation.egg-info/SOURCES.txt
bob.learn.activation.egg-info/dependency_links.txt
bob.learn.activation.egg-info/not-zip-safe
bob.learn.activation.egg-info/requires.txt
bob.learn.activation.egg-info/top_level.txt
bob/learn/__init__.py
bob/learn/activation/__init__.py
bob/learn/activation/activation.cpp
bob/learn/activation/identity.cpp
bob/learn/activation/linear.cpp
bob/learn/activation/logistic.cpp
bob/learn/activation/main.cpp
bob/learn/activation/mult_tanh.cpp
bob/learn/activation/tanh.cpp
bob/learn/activation/test.py
bob/learn/activation/version.cpp
bob/learn/activation/cpp/ActivationRegistry.cpp
bob/learn/activation/include/bob.learn.activation/Activation.h
bob/learn/activation/include/bob.learn.activation/api.h
bob/learn/activation/include/bob.learn.activation/config.h
doc/c_cpp_api.rst
doc/conf.py
doc/index.rst
doc/links.rst
doc/py_api.rst